pakk/README.md
pakk/__init__.py
pakk/__main__.py
pakk/cli.py
pakk/logger.py
pakk/module.py
pakk/actions/__init__.py
pakk/actions/clean.py
pakk/actions/configure.py
pakk/actions/dev.py
pakk/actions/environment.py
pakk/actions/init.py
pakk/actions/install.py
pakk/actions/list.py
pakk/actions/manager.py
pakk/actions/ros2.py
pakk/actions/setup.py
pakk/actions/source.py
pakk/actions/status.py
pakk/actions/tree.py
pakk/actions/update.py
pakk/args/__init__.py
pakk/args/base_args.py
pakk/args/install_args.py
pakk/args/manager_args.py
pakk/config/__init__.py
pakk/config/base.py
pakk/config/main_cfg.py
pakk/config/process.py
pakk/connector/__init__.py
pakk/connector/base.py
pakk/connector/cache.py
pakk/connector/git_generic.py
pakk/connector/local.py
pakk/connector/github/__init__.py
pakk/connector/github/config.py
pakk/connector/github/connector.py
pakk/connector/gitlab/__init__.py
pakk/connector/gitlab/config.py
pakk/connector/gitlab/connector.py
pakk/dependency_tree/__init__.py
pakk/dependency_tree/tree.py
pakk/dependency_tree/tree_printer.py
pakk/environments/__init__.py
pakk/environments/base.py
pakk/environments/linux.py
pakk/environments/loader.py
pakk/environments/old/dockerbase.py
pakk/environments/old/python/__init__.py
pakk/environments/old/python/python_local.py
pakk/environments/old/ros2/Dockerfile
pakk/environments/old/ros2/__init__.py
pakk/environments/old/ros2/base.py
pakk/environments/old/ros2/ros2_docker.py
pakk/environments/old/ros2/ros2_local.py
pakk/environments/parts/__init__.py
pakk/environments/parts/nginx.py
pakk/environments/parts/python.py
pakk/environments/parts/ros2.py
pakk/helper/__init__.py
pakk/helper/cfg_converter.py
pakk/helper/cli_util.py
pakk/helper/file_util.py
pakk/helper/loader.py
pakk/helper/lockfile.py
pakk/helper/module_importer.py
pakk/helper/progress.py
pakk/installer/__init__.py
pakk/installer/combining_installer.py
pakk/manager/__init__.py
pakk/manager/systemd/__init__.py
pakk/manager/systemd/unit_file_definition.py
pakk_package_manager-0.4.0.dist-info/METADATA
pakk_package_manager-0.4.0.dist-info/WHEEL
pakk_package_manager-0.4.0.dist-info/entry_points.txt
pakk_package_manager-0.4.0.dist-info/licenses/LICENSE
pakk_package_manager-0.4.0.dist-info/RECORD
