Metadata-Version: 2.3
Name: pakk-package-manager
Version: 0.4.0
Summary: Pakk Package Manager.
Project-URL: Homepage, https://github.com/icampus-wildau/pakk
Project-URL: Issues, https://github.com/icampus-wildau/pakk/issues
Author-email: Valentin Schröter <vasc9380@th-wildau.de>
License-File: LICENSE
Classifier: Programming Language :: Python :: 3
Requires-Python: >=3.10
Requires-Dist: braceexpand
Requires-Dist: click
Requires-Dist: click-aliases
Requires-Dist: extended-configparser
Requires-Dist: flock
Requires-Dist: graphviz
Requires-Dist: inquirerpy
Requires-Dist: jellyfish
Requires-Dist: jsons
Requires-Dist: markdown-plus
Requires-Dist: networkx
Requires-Dist: node-semver
Requires-Dist: prettytable
Requires-Dist: psutil
Requires-Dist: pyfiglet
Requires-Dist: pygithub
Requires-Dist: python-dotenv
Requires-Dist: python-gitlab>=3.0.0
Requires-Dist: pytz
Requires-Dist: requests
Requires-Dist: rich
Requires-Dist: semver
Requires-Dist: tqdm
